hydrobot/__init__.py
hydrobot/data_acquisition.py
hydrobot/data_sources.py
hydrobot/data_structure.py
hydrobot/do_processor.py
hydrobot/evaluator.py
hydrobot/filters.py
hydrobot/htmlmerger.py
hydrobot/hydrobot_initialiser.py
hydrobot/plotter.py
hydrobot/processor.py
hydrobot/rf_processor.py
hydrobot/tasks.py
hydrobot/utils.py
hydrobot/config/Three_letter_codes.yaml
hydrobot/config/__init__.py
hydrobot/config/horizons_source.py
hydrobot/config/generic_template/hydrobot_template.accdb
hydrobot/config/generic_template/hydrobot_template.hts
hydrobot/config/horizons_sql/atmospheric_pressure_check.sql
hydrobot/config/horizons_sql/calibration_query.sql
hydrobot/config/horizons_sql/dissolved_oxygen_check.sql
hydrobot/config/horizons_sql/hydro_inspection.sql
hydrobot/config/horizons_sql/non_conformances.sql
hydrobot/config/horizons_sql/rainfall_check.sql
hydrobot/config/horizons_sql/rainfall_site_inspection.sql
hydrobot/config/horizons_sql/site_info_lookup.sql
hydrobot/config/horizons_sql/sonde_calibration_query.sql
hydrobot/config/horizons_sql/three_letter_site_code.sql
hydrobot/config/horizons_sql/water_temperature_check.sql
hydrobot/config/template_families/air_temperature/hydrobot_run_at.py
hydrobot/config/template_families/air_temperature/hydrobot_yaml_config_at.yaml
hydrobot/config/template_families/atmospheric_pressure/hydrobot_run_ap.py
hydrobot/config/template_families/atmospheric_pressure/hydrobot_yaml_config_ap.yaml
hydrobot/config/template_families/conductivity/hydrobot_run_cond.py
hydrobot/config/template_families/conductivity/hydrobot_yaml_config_conductivity.yaml
hydrobot/config/template_families/dissolved_oxygen/hydrobot_run_do.py
hydrobot/config/template_families/dissolved_oxygen/hydrobot_yaml_config_do.yaml
hydrobot/config/template_families/ph/hydrobot_run_ph.py
hydrobot/config/template_families/ph/hydrobot_yaml_config_ph.yaml
hydrobot/config/template_families/rainfall/hydrobot_run_rain.py
hydrobot-0.9.12.dist-info/licenses/AUTHORS.rst
hydrobot-0.9.12.dist-info/licenses/LICENSE
hydrobot-0.9.12.dist-info/METADATA
hydrobot-0.9.12.dist-info/WHEEL
hydrobot-0.9.12.dist-info/top_level.txt
hydrobot-0.9.12.dist-info/RECORD
