Metadata-Version: 2.4
Name: hydrobot
Version: 0.9.12
Summary: A suite of processing tools for Hilltop hydrological data.
Author-email: Nic Mostert <nicolas.mostert@horizons.govt.nz>, Sam Irvine <sam.irvine@horizons.govt.nz>
License: GNU General Public License v3
Project-URL: Homepage, https://github.com/HorizonsRC/hydrobot
Project-URL: Issues, https://github.com/HorizonsRC/hydrobot/issues
Project-URL: Documentation, https://hydrobot.readthedocs.io
Project-URL: Package, https://pypi.org/project/hydrobot
Keywords: hydrology, automation, pandas, hilltop, hilltop-py, HorizonsRC
Classifier: Development Status :: 3 - Alpha
Classifier: Intended Audience :: Developers
Classifier: License :: OSI Approved :: GNU General Public License v3 (GPLv3)
Classifier: Natural Language :: English
Classifier: Programming Language :: Python :: 3.11
Requires-Python: >=3.11
License-File: LICENSE
License-File: AUTHORS.rst
Requires-Dist: hilltop-py>=2.3.1
Requires-Dist: data-annalist>=0.4.4
Requires-Dist: matplotlib>=3.8.0
Requires-Dist: defusedxml>=0.7.1
Requires-Dist: plotly>=5.20.0
Requires-Dist: streamlit>=1.33.0
Requires-Dist: pyyaml>=6.0.1
Requires-Dist: numpy==1.26.4
Requires-Dist: openpyxl>=3.1.5
Requires-Dist: SQLAlchemy~=2.0.30
Requires-Dist: pyodbc==5.1.0
Requires-Dist: ruamel.yaml==0.18.6
Requires-Dist: xmltodict==0.14.2
Provides-Extra: test
Requires-Dist: pytest>=7.4.2; extra == "test"
Requires-Dist: pytest-cov>=4.1.0; extra == "test"
Requires-Dist: pytest-dependency>=0.5.2; extra == "test"
Requires-Dist: pytest-mock>=3.12.0; extra == "test"
Provides-Extra: dev
Requires-Dist: ruff>=0.1.6; extra == "dev"
Requires-Dist: ruff-lsp>=0.0.45; extra == "dev"
Requires-Dist: pre-commit>=3.5.0; extra == "dev"
Requires-Dist: build>=1.0.0; extra == "dev"
Provides-Extra: docs
Requires-Dist: Sphinx>=7.2.6; extra == "docs"
Requires-Dist: furo>=2023.9.10; extra == "docs"
Dynamic: license-file
